thief_snapshot/__init__.py
thief_snapshot/__main__.py
thief_snapshot/copy_settings.py
thief_snapshot/example_settings.ini
thief_snapshot/cameras/__init__.py
thief_snapshot/cameras/_amcrest.py
thief_snapshot/cameras/base.py
thief_snapshot/motion_detection/__init__.py
thief_snapshot/motion_detection/_amcrest.py
thief_snapshot/motion_detection/base.py
thief_snapshot/presence_detection/__init__.py
thief_snapshot/presence_detection/_ddwrt.py
thief_snapshot/presence_detection/base.py
thief_snapshot-0.2.0.dist-info/DESCRIPTION.rst
thief_snapshot-0.2.0.dist-info/METADATA
thief_snapshot-0.2.0.dist-info/RECORD
thief_snapshot-0.2.0.dist-info/WHEEL
thief_snapshot-0.2.0.dist-info/entry_points.txt
thief_snapshot-0.2.0.dist-info/metadata.json
thief_snapshot-0.2.0.dist-info/top_level.txt
