Metadata-Version: 2.0
Name: thief-snapshot
Version: 0.2.0
Summary: Detects motion with a camera and sends snapshots using a telegram chatbot if your phone is not on wifi.
Home-page: https://github.com/pawl/thief-snapshot
Author: Paul Brown
Author-email: paul90brown+pypi@gmail.com
License: UNKNOWN
Platform: UNKNOWN
Classifier: Programming Language :: Python :: 2
Classifier: Programming Language :: Python :: 3
Requires-Dist: python-telegram-bot (==6.1.0)
Provides-Extra: amcrest
Requires-Dist: amcrest (==1.2.0); extra == 'amcrest'
